{"events": [
    {
        "name": "SpeeDons 6",
        "start": "2026-05-07",
        "end": "2026-05-10",
        "url": "https://speeDons.fr/"
    },
    {
        "name": "BSG Annual 2026 (Benelux Speedrunner Gathering)",
        "start": "2026-07-25",
        "end": "2026-08-01",
        "url": "https://bsgmarathon.com/events/bsg2026"
    },
    {
        "name": "ESA Summer 2026 (European Speedrunner Assembly)",
        "start": "2026-08-01",
        "end": "2026-08-08",
        "url": "https://esamarathon.com/"
    }
]}